.bumpversion.cfg
LICENSE.txt
MANIFEST.in
README.rst
README_continuous_integration.md
pypackage.mk
requirements.txt
setup.py
src/PyContracts3.egg-info/PKG-INFO
src/PyContracts3.egg-info/SOURCES.txt
src/PyContracts3.egg-info/dependency_links.txt
src/PyContracts3.egg-info/requires.txt
src/PyContracts3.egg-info/top_level.txt
src/contracts/__init__.py
src/contracts/backported.py
src/contracts/docstring_parsing.py
src/contracts/enabling.py
src/contracts/inspection.py
src/contracts/interface.py
src/contracts/main.py
src/contracts/main_actual.py
src/contracts/metaclass.py
src/contracts/pyparsing_utils.py
src/contracts/syntax.py
src/contracts/test_registrar.py
src/contracts/utils.py
src/contracts/library/__init__.py
src/contracts/library/arithmetic.py
src/contracts/library/array.py
src/contracts/library/array_ops.py
src/contracts/library/attributes.py
src/contracts/library/collection.py
src/contracts/library/comparison.py
src/contracts/library/compositions.py
src/contracts/library/datetime_tz.py
src/contracts/library/dicts.py
src/contracts/library/dummy.py
src/contracts/library/extensions.py
src/contracts/library/files.py
src/contracts/library/isinstance_imp.py
src/contracts/library/lists.py
src/contracts/library/map.py
src/contracts/library/miscellaneous_aliases.py
src/contracts/library/scoped_variables.py
src/contracts/library/separate_context.py
src/contracts/library/seq.py
src/contracts/library/sets.py
src/contracts/library/simple_values.py
src/contracts/library/strings.py
src/contracts/library/suggester.py
src/contracts/library/tuple.py
src/contracts/library/types_misc.py
src/contracts/library/variables.py
src/contracts/testing/__init__.py
src/contracts/testing/array_extended_test.py
src/contracts/testing/friendliness_statistics.py
src/contracts/testing/test_class_contracts.py
src/contracts/testing/test_decorator.py
src/contracts/testing/test_docstring_parsing.py
src/contracts/testing/test_idioms.py
src/contracts/testing/test_meta.py
src/contracts/testing/test_multiple.py
src/contracts/testing/test_new_contract.py
src/contracts/testing/test_particulars.py
src/contracts/testing/test_pickling.py
src/contracts/testing/test_simple.py
